dc_avro/__init__.py
dc_avro/_diff.py
dc_avro/_schema_utils.py
dc_avro/_types.py
dc_avro/exceptions.py
dc_avro/main.py
dc_avro-0.13.0.dist-info/METADATA
dc_avro-0.13.0.dist-info/WHEEL
dc_avro-0.13.0.dist-info/entry_points.txt
dc_avro-0.13.0.dist-info/licenses/LICENSE
dc_avro-0.13.0.dist-info/RECORD
