Metadata-Version: 2.4
Name: dc-avro
Version: 0.13.0
Summary: 
License: MIT
License-File: LICENSE
Keywords: avro,schemas,dataclasses,pydantic,lint
Author: Marcos Schroh
Author-email: marcos.schroh@kpn.com
Requires-Python: >=3.10,<4.0
Classifier: Intended Audience :: Developers
Classifier: License :: OSI Approved :: MIT License
Classifier: Programming Language :: Python :: 3
Classifier: Programming Language :: Python :: 3.10
Classifier: Programming Language :: Python :: 3.11
Classifier: Programming Language :: Python :: 3.12
Classifier: Programming Language :: Python :: 3.13
Classifier: Programming Language :: Python :: 3.14
Classifier: Programming Language :: Python :: Implementation :: CPython
Classifier: Topic :: Software Development :: Libraries :: Application Frameworks
Classifier: Topic :: System :: Distributed Computing
Classifier: Topic :: System :: Networking
Requires-Dist: aiofiles (>=24.1.0,<25.0)
Requires-Dist: dataclasses-avroschema (>=0.57.2)
Requires-Dist: deepdiff (>=6.2.3,<9.0.0)
Requires-Dist: httpx (>=0.23.3,<0.29.0)
Requires-Dist: truststore (>=0.10.1,<0.11.0) ; python_version >= "3.10" and python_version < "4.0"
Requires-Dist: typer[all] (>=0.9,<0.17)
